crowdsec_local_mcp/__init__.py
crowdsec_local_mcp/__main__.py
crowdsec_local_mcp/mcp_core.py
crowdsec_local_mcp/mcp_scenarios.py
crowdsec_local_mcp/mcp_waf.py
crowdsec_local_mcp/setup_cli.py
crowdsec_local_mcp/compose/waf-test/.gitignore
crowdsec_local_mcp/compose/waf-test/docker-compose.yml
crowdsec_local_mcp/compose/waf-test/crowdsec/init-bouncer.sh
crowdsec_local_mcp/compose/waf-test/crowdsec/acquis.d/appsec.yaml
crowdsec_local_mcp/compose/waf-test/crowdsec/appsec-configs/mcp-appsec.yaml.template
crowdsec_local_mcp/compose/waf-test/nginx/Dockerfile
crowdsec_local_mcp/compose/waf-test/nginx/nginx.conf
crowdsec_local_mcp/compose/waf-test/nginx/crowdsec/crowdsec-openresty-bouncer.conf
crowdsec_local_mcp/compose/waf-test/nginx/site-enabled/default-site.conf
crowdsec_local_mcp/compose/waf-test/rules/.gitkeep
crowdsec_local_mcp/compose/waf-test/rules/base-config.yaml
crowdsec_local_mcp/prompts/prompt-scenario-deploy.txt
crowdsec_local_mcp/prompts/prompt-scenario-examples.txt
crowdsec_local_mcp/prompts/prompt-scenario.txt
crowdsec_local_mcp/prompts/prompt-waf-deploy.txt
crowdsec_local_mcp/prompts/prompt-waf-examples.txt
crowdsec_local_mcp/prompts/prompt-waf.txt
crowdsec_local_mcp/yaml-schemas/appsec_rules_schema.yaml
crowdsec_local_mcp/yaml-schemas/scenario_schema.yaml
crowdsec_local_mcp-0.2.0.dist-info/licenses/LICENSE
crowdsec_local_mcp-0.2.0.dist-info/METADATA
crowdsec_local_mcp-0.2.0.dist-info/WHEEL
crowdsec_local_mcp-0.2.0.dist-info/entry_points.txt
crowdsec_local_mcp-0.2.0.dist-info/top_level.txt
crowdsec_local_mcp-0.2.0.dist-info/RECORD
