Metadata-Version: 2.4
Name: crowdsec-local-mcp
Version: 0.2.0
Summary: An MCP exposing prompts and tools to help users write WAF rules, scenarios etc.
Requires-Python: >=3.12
License-File: LICENSE
Requires-Dist: jsonschema>=4.25.1
Requires-Dist: mcp>=1.15.0
Requires-Dist: pyyaml>=6.0.3
Requires-Dist: requests>=2.32.5
Dynamic: license-file
